[{"childs":[{"_content":"eat\nsleep\npoop\nplay","_highlighted":false,"_mode":"FreeNote","_title":"everyday life"},{"_highlighted":false,"_mode":"TodoList","_tasks":[{"_selectedTask":false,"_task":"no play need to sleep"},{"_selectedTask":false,"_subTasks":[{"_selectedTask":false,"_subTasks":[{"_selectedTask":false,"_task":"pre-cooked "}],"_task":"eat takeout"}],"_task":"eat"},{"_selectedTask":false,"_subTasks":[{"_selectedTask":false,"_task":"work 996"}],"_task":"work"}],"_title":"suck life\n"},{"_content":"I have a plan\n? how to earn 1 yi\n! It's not for everybody\n= marry a rich man\n> win lottery","_highlighted":false,"_mode":"FreeNote","_title":"critical thinking syntax"},{"_content":"在很长一段时间内，32支球队参加世界杯决赛圈，是业界公认较为合理的规模，也是广大球迷最熟悉的世界杯赛制。因为32支球队正好可以分为8个小组，每个小组4支队，从小组赛至决赛一共进行64场，耗时约30天时间，刚刚为夏天的一个月时间，这个时间一般都是欧洲主要联赛的休赛期。\n\n2022年卡塔尔世界杯后，国际足联宣布从2026年美国、加拿大、墨西哥世界杯起，决赛圈扩军至48支球队参加。","_highlighted":false,"_mode":"FreeNote","_title":"text wrap"}],"title":"demo"}]